giphpy/__init__.py
giphpy/api.py
giphpy/async_api.py
giphpy/core.py
giphpy/enums.py
giphpy/models.py
giphpy/py.typed
giphpy-0.1.2.dist-info/METADATA
giphpy-0.1.2.dist-info/WHEEL
giphpy-0.1.2.dist-info/LICENSE
giphpy-0.1.2.dist-info/RECORD
